appia/__init__.py
appia/appia.py
appia/parsers/__init__.py
appia/parsers/database_parser.py
appia/parsers/process_parser.py
appia/parsers/user_settings.py
appia/parsers/utilities_parser.py
appia/plotters/__init__.py
appia/plotters/auto_plot.py
appia/plotters/manual_plot_FPLC.R
appia/plotters/manual_plot_HPLC.R
appia/processors/__init__.py
appia/processors/core.py
appia/processors/database.py
appia/processors/experiment.py
appia/processors/fplc.py
appia/processors/gui.py
appia/processors/hplc.py
appia-7.3.2.dist-info/LICENSE
appia-7.3.2.dist-info/METADATA
appia-7.3.2.dist-info/WHEEL
appia-7.3.2.dist-info/entry_points.txt
appia-7.3.2.dist-info/top_level.txt
appia-7.3.2.dist-info/RECORD
