Metadata-Version: 2.1
Name: appia
Version: 7.3.2
Summary: Chromatography processing made easy
Home-page: https://github.com/PlethoraChutney/Appia
Author: Rich Posert
Author-email: posert@ohsu.edu
Classifier: License :: OSI Approved :: MIT License
Requires-Python: >=3.6
License-File: LICENSE
Requires-Dist: couchdb
Requires-Dist: pandas
Requires-Dist: plotly
Requires-Dist: kaleido
